pyTruthTable/__init__.py
pyTruthTable/pyTruthTable.py
pyTruthTable-0.0.2.dist-info/LICENSE
pyTruthTable-0.0.2.dist-info/METADATA
pyTruthTable-0.0.2.dist-info/WHEEL
pyTruthTable-0.0.2.dist-info/top_level.txt
pyTruthTable-0.0.2.dist-info/RECORD
