Metadata-Version: 2.1
Name: pyTruthTable
Version: 0.0.2
Summary: A python tool for logic clauses analysis and binary operations
Home-page: https://leomariga.github.io/pyTruthTable/
Author: Leonardo Mariga
Author-email: leomariga@gmail.com
License: UNKNOWN
Project-URL: Documentation, https://leomariga.github.io/pyTruthTable/
Project-URL: Source, https://github.com/leomariga/pyTruthTable
Keywords: truth table python generation logic pandas dataframe
Platform: UNKNOWN
Classifier: Programming Language :: Python :: 3
Classifier: License :: OSI Approved :: MIT License
Classifier: Operating System :: OS Independent
Requires-Python: >=3.6
